igePAL/__init__.py
igePAL/_igePAL.cp37-win32.pyd
igePAL-0.0.6.dist-info/LICENSE
igePAL-0.0.6.dist-info/METADATA
igePAL-0.0.6.dist-info/WHEEL
igePAL-0.0.6.dist-info/top_level.txt
igePAL-0.0.6.dist-info/RECORD
